demokit/__init__.py
demokit/__main__.py
demokit/catalog.template.html
demokit/index.html
demokit/requirements.txt
demokit/splash.html
demokit/apps/APP-A0/Dockerfile
demokit/apps/APP-A0/app-info.json
demokit/apps/APP-A0/public/index.html
demokit/apps/APP-A1/Dockerfile
demokit/apps/APP-A1/app-info.json
demokit/apps/APP-A1/public/index.html
demokit/apps/APP-A10/Dockerfile
demokit/apps/APP-A10/app-info.json
demokit/apps/APP-A10/public/index.html
demokit/apps/APP-A2/Dockerfile
demokit/apps/APP-A2/app-info.json
demokit/apps/APP-A2/public/index.html
demokit/apps/APP-A3/Dockerfile
demokit/apps/APP-A3/app-info.json
demokit/apps/APP-A3/index.php
demokit/apps/APP-A4/Dockerfile
demokit/apps/APP-A4/app-info.json
demokit/apps/APP-A4/public/index.html
demokit/apps/APP-A4/public/index.html.old
demokit/apps/APP-A5/Dockerfile
demokit/apps/APP-A5/app-info.json
demokit/apps/APP-A5/public/index.html
demokit/apps/APP-A6/Dockerfile
demokit/apps/APP-A6/app-info.json
demokit/apps/APP-A6/public/index.html
demokit/apps/APP-A7/Dockerfile
demokit/apps/APP-A7/app-info.json
demokit/apps/APP-A7/public/index.html
demokit/apps/APP-A7_2/Dockerfile
demokit/apps/APP-A7_2/app-info.json
demokit/apps/APP-A7_2/public/index.html
demokit/apps/APP-A8/Dockerfile
demokit/apps/APP-A8/app-info.json
demokit/apps/APP-A8/public/index.html
demokit/apps/APP-A9/Dockerfile
demokit/apps/APP-A9/app-info.json
demokit/apps/APP-A9/public/index.html
demokit/apps/APP-BONUS0/Dockerfile
demokit/apps/APP-BONUS0/app-info.json
demokit/apps/APP-BONUS0/public/index.html
demokit/apps/APP-BONUS1/Dockerfile
demokit/apps/APP-BONUS1/app-info.json
demokit/apps/APP-BONUS1/public/index.html
demokit/apps/APP-BONUS2/Dockerfile
demokit/apps/APP-BONUS2/app-info.json
demokit/apps/APP-BONUS2/public/index.html
demokit/apps/APP-BONUS3/Dockerfile
demokit/apps/APP-BONUS3/app-info.json
demokit/apps/APP-BONUS3/public/index.html
demokit/apps/APP-BONUS4/Dockerfile
demokit/apps/APP-BONUS4/app-info.json
demokit/apps/APP-BONUS4/public/index.html
demokit-2.0.dist-info/entry_points.txt
demokit-2.0.dist-info/WHEEL
demokit-2.0.dist-info/METADATA
demokit-2.0.dist-info/RECORD
