Metadata-Version: 2.4
Name: demokit
Version: 2.0
Summary: Kit de démonstration d'applications
Author-email: guillaumefe <guillaume.ferron@gmail.com>
Requires-Dist: click
Requires-Dist: setuptools
Project-URL: Home, https://github.com/guillaumefe/owasp
